[
{"Name":"continue","Bounds":"638,48,109,26"},
{"Name":"continue_x","Bounds":"749,48,109,26"},
{"Name":"next_building","Bounds":"638,76,96,26"},
{"Name":"next_building_x","Bounds":"736,76,96,26"},
{"Name":"next_level","Bounds":"872,89,96,26"},
{"Name":"next_level_x","Bounds":"638,104,96,26"},
{"Name":"clear_screen","Bounds":"736,104,96,26"},
{"Name":"clear_screen_x","Bounds":"872,117,96,26"},
{"Name":"credits","Bounds":"638,132,96,26"},
{"Name":"credits_x","Bounds":"736,132,96,26"},
{"Name":"fail_getHint","Bounds":"310,1,210,135"},
{"Name":"fail_getHint_x","Bounds":"310,138,210,135"},
{"Name":"fail_selectLevel","Bounds":"522,1,114,135"},
{"Name":"fail_selectLevel_x","Bounds":"522,138,114,135"},
{"Name":"fail_tryAgain","Bounds":"1,1,307,135"},
{"Name":"fail_tryAgain_x","Bounds":"1,138,307,135"},
{"Name":"next_button","Bounds":"834,76,36,26"},
{"Name":"next_button_x","Bounds":"834,104,36,26"},
{"Name":"ok_button","Bounds":"874,1,76,42"},
{"Name":"ok_button_x","Bounds":"874,45,76,42"},
{"Name":"prev_button","Bounds":"834,132,36,26"},
{"Name":"prev_button_x","Bounds":"834,160,36,26"},
{"Name":"help","Bounds":"872,145,96,26"},
{"Name":"help_x","Bounds":"638,160,96,26"},
{"Name":"hiscore","Bounds":"736,160,96,26"},
{"Name":"hiscore_x","Bounds":"872,173,96,26"},
{"Name":"quit","Bounds":"638,188,96,26"},
{"Name":"quit_X","Bounds":"736,188,96,26"},
{"Name":"play","Bounds":"638,1,116,45"},
{"Name":"play_x","Bounds":"756,1,116,45"},
{"Name":"replay_intro","Bounds":"834,201,96,26"},
{"Name":"replay_intro_x","Bounds":"638,216,96,26"},
{"Name":"skip_intro","Bounds":"736,216,96,26"},
{"Name":"skip_intro_x","Bounds":"834,229,96,26"},
{"Name":"start_up","Bounds":"638,244,96,26"},
{"Name":"start_up_x","Bounds":"736,244,96,26"}
]